classification_names
