Metadata-Version: 1.0
Name: classification-names
Version: 2.1.3
Summary: 人名，公司或机构名称分类
Home-page: https://gitlab.kingdomai.com/wangqiang/name_classification/wangqiang/classification_names
Author: it-wqll
Author-email: wangqiang6480@163.com
License: MIT Licence
Keywords: pip,classification_names
Platform: any
